c4m/pdk/gf180mcu/__init__.py
c4m/pdk/gf180mcu/klayout.py
c4m/pdk/gf180mcu/models/__init__.py
c4m/pdk/gf180mcu/models/all.spice
c4m/pdk/gf180mcu/models/design.ngspice
c4m/pdk/gf180mcu/models/sm141064.ngspice
c4m/pdk/gf180mcu/pdkmaster.py
c4m/pdk/gf180mcu/pyspice.py
c4m/pdk/gf180mcu/spice.py
c4m/pdk/gf180mcu/stdcell.py
c4m_pdk_gf180mcu-0.0.11.dist-info/METADATA
c4m_pdk_gf180mcu-0.0.11.dist-info/WHEEL
c4m_pdk_gf180mcu-0.0.11.dist-info/entry_points.txt
c4m_pdk_gf180mcu-0.0.11.dist-info/licenses/LICENSE.md
c4m_pdk_gf180mcu-0.0.11.dist-info/RECORD
